fractus-0.1.12.dist-info/METADATA
fractus-0.1.12.dist-info/WHEEL
fractus-0.1.12.dist-info/licenses/LICENSE
fractus/__init__.py
fractus/fractus.cpython-39-x86_64-linux-gnu.so
fractus-0.1.12.dist-info/RECORD
