Metadata-Version: 2.4
Name: fractus
Version: 0.1.12
Requires-Dist: cffi>=1.16.0
License-File: LICENSE
Summary: Cryptographic attack library for Rust and Python
Keywords: crypto,attack
Author: GlacierSG <iamglaciersg@gmail.com>
Author-email: GlacierSG <iamglaciersg@gmail.com>
License: MIT
Project-URL: Source Code, https://github.com/GlacierSG/fractus
